ASL_alnum_recognizer/__init__.py
ASL_alnum_recognizer/recognize.py
ASL_alnum_recognizer/models/signLanguageDetectoralpnum.h5
ASL_Alpnum_Recognizer-0.6.dist-info/METADATA
ASL_Alpnum_Recognizer-0.6.dist-info/WHEEL
ASL_Alpnum_Recognizer-0.6.dist-info/entry_points.txt
ASL_Alpnum_Recognizer-0.6.dist-info/top_level.txt
ASL_Alpnum_Recognizer-0.6.dist-info/RECORD
